pyentrypoint/__init__.py
pyentrypoint/__main__.py
pyentrypoint/command.py
pyentrypoint/config.py
pyentrypoint/configparser.py
pyentrypoint/constants.py
pyentrypoint/container.py
pyentrypoint/docker_links.py
pyentrypoint/entrypoint.py
pyentrypoint/links.py
pyentrypoint/logs.py
pyentrypoint/reloader.py
pyentrypoint/runner.py
pyentrypoint-0.8.0.dist-info/entry_points.txt
pyentrypoint-0.8.0.dist-info/WHEEL
pyentrypoint-0.8.0.dist-info/METADATA
pyentrypoint-0.8.0.dist-info/RECORD
