Metadata-Version: 2.1
Name: pyentrypoint
Version: 0.8.0
Summary: pyentrypoint manages entrypoints in Docker containers.
Home-page: http://github.com/cmehay/pyentrypoint
License: WTFPL
Author: Christophe Mehay
Author-email: cmehay@nospam.student.42.fr
Requires-Python: >=3.8.0,<3.11
Classifier: Development Status :: 1 - Planning
Classifier: License :: OSI Approved :: BSD License
Classifier: License :: Other/Proprietary License
Classifier: Natural Language :: English
Classifier: Operating System :: POSIX :: Linux
Classifier: Programming Language :: Python
Classifier: Programming Language :: Python :: 2
Classifier: Programming Language :: Python :: 2.7
Classifier: Programming Language :: Python :: 3
Classifier: Programming Language :: Python :: 3.10
Classifier: Programming Language :: Python :: 3.6
Classifier: Programming Language :: Python :: 3.8
Classifier: Programming Language :: Python :: 3.9
Classifier: Topic :: System :: Installation/Setup
Requires-Dist: colorlog
Requires-Dist: jinja2
Requires-Dist: pyyaml
Requires-Dist: six
Requires-Dist: toml
Requires-Dist: watchdog (>=0.10,<0.11)
